[
    {
        "relation": [
            "delegate_permission/common.handle_all_urls"
        ],
        "target": {
            "namespace": "android_app",
            "package_name": "com.familytree.family_tree.dev",
            "sha256_cert_fingerprints": [
                "74:3F:ED:C4:8E:8D:8F:53:CF:73:F0:06:C8:C2:DC:A9:AC:01:D6:05:9E:32:9E:FE:D0:8F:DA:B2:FA:3C:71:B3",
                "59:1E:87:01:4E:69:BB:3F:03:51:4A:1F:E6:2F:43:B7:31:34:D4:1A:5B:0C:47:1E:F0:85:29:48:24:D9:84:65"
            ]
        }
    },
    {
        "relation": [
            "delegate_permission/common.handle_all_urls"
        ],
        "target": {
            "namespace": "android_app",
            "package_name": "com.familytree.family_tree",
            "sha256_cert_fingerprints": [
                "74:3F:ED:C4:8E:8D:8F:53:CF:73:F0:06:C8:C2:DC:A9:AC:01:D6:05:9E:32:9E:FE:D0:8F:DA:B2:FA:3C:71:B3",
                "59:1E:87:01:4E:69:BB:3F:03:51:4A:1F:E6:2F:43:B7:31:34:D4:1A:5B:0C:47:1E:F0:85:29:48:24:D9:84:65"
            ]
        }
    },
    {
        "relation": [
            "delegate_permission/common.handle_all_urls"
        ],
        "target": {
            "namespace": "android_app",
            "package_name": "com.familytree.family_tree.demo",
            "sha256_cert_fingerprints": [
                "74:3F:ED:C4:8E:8D:8F:53:CF:73:F0:06:C8:C2:DC:A9:AC:01:D6:05:9E:32:9E:FE:D0:8F:DA:B2:FA:3C:71:B3",
                "59:1E:87:01:4E:69:BB:3F:03:51:4A:1F:E6:2F:43:B7:31:34:D4:1A:5B:0C:47:1E:F0:85:29:48:24:D9:84:65"
            ]
        }
    },
    {
        "relation": [
            "delegate_permission/common.handle_all_urls"
        ],
        "target": {
            "namespace": "android_app",
            "package_name": "com.familytree.family_tree.rc",
            "sha256_cert_fingerprints": [
                "74:3F:ED:C4:8E:8D:8F:53:CF:73:F0:06:C8:C2:DC:A9:AC:01:D6:05:9E:32:9E:FE:D0:8F:DA:B2:FA:3C:71:B3",
                "59:1E:87:01:4E:69:BB:3F:03:51:4A:1F:E6:2F:43:B7:31:34:D4:1A:5B:0C:47:1E:F0:85:29:48:24:D9:84:65"
            ]
        }
    }
]
